korml/metadata.py
korml-0.0.2.dist-info/METADATA
korml-0.0.2.dist-info/WHEEL
korml-0.0.2.dist-info/entry_points.txt
korml-0.0.2.dist-info/RECORD
