Metadata-Version: 2.4
Name: korml
Version: 0.0.2
Summary: A korml Parser and Emitter
Project-URL: Source, https://ambhora.codes/software/korml
Author-email: Jayesh Badwaik <j.badwaik@fz-juelich.de>
License-Expression: Apache-2.0
Requires-Dist: pexpect
Requires-Dist: semver
